mstarpypost/__init__.py
mstarpypost/batch_post.py
mstarpypost/colorscales.py
mstarpypost/config.py
mstarpypost/gui_config.py
mstarpypost/gui_plot.py
mstarpypost/mstarvtk.py
mstarpypost/particles.py
mstarpypost/reports.py
mstarpypost/resources.py
mstarpypost/util.py
mstarpypost/vtk_meta.py
mstarpypost-1.0.14.dist-info/LICENSE.txt
mstarpypost-1.0.14.dist-info/METADATA
mstarpypost-1.0.14.dist-info/WHEEL
mstarpypost-1.0.14.dist-info/entry_points.txt
mstarpypost-1.0.14.dist-info/top_level.txt
mstarpypost-1.0.14.dist-info/RECORD
